{
    "CrossLanguagePackageId": "Microsoft.AzureSphere",
    "CrossLanguageDefinitionId": {
        "azure.mgmt.sphere.models.Resource": "Azure.ResourceManager.CommonTypes.Resource",
        "azure.mgmt.sphere.models.TrackedResource": "Azure.ResourceManager.CommonTypes.TrackedResource",
        "azure.mgmt.sphere.models.Catalog": "Microsoft.AzureSphere.Catalog",
        "azure.mgmt.sphere.models.CatalogProperties": "Microsoft.AzureSphere.CatalogProperties",
        "azure.mgmt.sphere.models.CatalogUpdate": "Microsoft.AzureSphere.CatalogUpdate",
        "azure.mgmt.sphere.models.ProxyResource": "Azure.ResourceManager.CommonTypes.ProxyResource",
        "azure.mgmt.sphere.models.Certificate": "Microsoft.AzureSphere.Certificate",
        "azure.mgmt.sphere.models.CertificateChainResponse": "Microsoft.AzureSphere.CertificateChainResponse",
        "azure.mgmt.sphere.models.CertificateProperties": "Microsoft.AzureSphere.CertificateProperties",
        "azure.mgmt.sphere.models.ClaimDevicesRequest": "Microsoft.AzureSphere.ClaimDevicesRequest",
        "azure.mgmt.sphere.models.CountElementsResponse": "Microsoft.AzureSphere.CountElementsResponse",
        "azure.mgmt.sphere.models.CountDevicesResponse": "Microsoft.AzureSphere.CountDevicesResponse",
        "azure.mgmt.sphere.models.Deployment": "Microsoft.AzureSphere.Deployment",
        "azure.mgmt.sphere.models.DeploymentProperties": "Microsoft.AzureSphere.DeploymentProperties",
        "azure.mgmt.sphere.models.Device": "Microsoft.AzureSphere.Device",
        "azure.mgmt.sphere.models.DeviceGroup": "Microsoft.AzureSphere.DeviceGroup",
        "azure.mgmt.sphere.models.DeviceGroupProperties": "Microsoft.AzureSphere.DeviceGroupProperties",
        "azure.mgmt.sphere.models.DeviceGroupUpdate": "Microsoft.AzureSphere.DeviceGroupUpdate",
        "azure.mgmt.sphere.models.DeviceGroupUpdateProperties": "Microsoft.AzureSphere.DeviceGroupUpdateProperties",
        "azure.mgmt.sphere.models.DeviceInsight": "Microsoft.AzureSphere.DeviceInsight",
        "azure.mgmt.sphere.models.DeviceProperties": "Microsoft.AzureSphere.DeviceProperties",
        "azure.mgmt.sphere.models.DeviceUpdate": "Microsoft.AzureSphere.DeviceUpdate",
        "azure.mgmt.sphere.models.DeviceUpdateProperties": "Microsoft.AzureSphere.DeviceUpdateProperties",
        "azure.mgmt.sphere.models.ErrorAdditionalInfo": "Azure.ResourceManager.CommonTypes.ErrorAdditionalInfo",
        "azure.mgmt.sphere.models.ErrorDetail": "Azure.ResourceManager.CommonTypes.ErrorDetail",
        "azure.mgmt.sphere.models.ErrorResponse": "Azure.ResourceManager.CommonTypes.ErrorResponse",
        "azure.mgmt.sphere.models.GenerateCapabilityImageRequest": "Microsoft.AzureSphere.GenerateCapabilityImageRequest",
        "azure.mgmt.sphere.models.Image": "Microsoft.AzureSphere.Image",
        "azure.mgmt.sphere.models.ImageProperties": "Microsoft.AzureSphere.ImageProperties",
        "azure.mgmt.sphere.models.ListDeviceGroupsRequest": "Microsoft.AzureSphere.ListDeviceGroupsRequest",
        "azure.mgmt.sphere.models.Operation": "Azure.ResourceManager.CommonTypes.Operation",
        "azure.mgmt.sphere.models.OperationDisplay": "Azure.ResourceManager.CommonTypes.OperationDisplay",
        "azure.mgmt.sphere.models.Product": "Microsoft.AzureSphere.Product",
        "azure.mgmt.sphere.models.ProductProperties": "Microsoft.AzureSphere.ProductProperties",
        "azure.mgmt.sphere.models.ProductUpdate": "Microsoft.AzureSphere.ProductUpdate",
        "azure.mgmt.sphere.models.ProductUpdateProperties": "Microsoft.AzureSphere.ProductUpdateProperties",
        "azure.mgmt.sphere.models.ProofOfPossessionNonceRequest": "Microsoft.AzureSphere.ProofOfPossessionNonceRequest",
        "azure.mgmt.sphere.models.ProofOfPossessionNonceResponse": "Microsoft.AzureSphere.ProofOfPossessionNonceResponse",
        "azure.mgmt.sphere.models.SignedCapabilityImageResponse": "Microsoft.AzureSphere.SignedCapabilityImageResponse",
        "azure.mgmt.sphere.models.SystemData": "Azure.ResourceManager.CommonTypes.SystemData",
        "azure.mgmt.sphere.models.Origin": "Azure.ResourceManager.CommonTypes.Origin",
        "azure.mgmt.sphere.models.ActionType": "Azure.ResourceManager.CommonTypes.ActionType",
        "azure.mgmt.sphere.models.CreatedByType": "Azure.ResourceManager.CommonTypes.createdByType",
        "azure.mgmt.sphere.models.ProvisioningState": "Microsoft.AzureSphere.ProvisioningState",
        "azure.mgmt.sphere.models.RegionalDataBoundary": "Microsoft.AzureSphere.RegionalDataBoundary",
        "azure.mgmt.sphere.models.ImageType": "Microsoft.AzureSphere.ImageType",
        "azure.mgmt.sphere.models.OSFeedType": "Microsoft.AzureSphere.OSFeedType",
        "azure.mgmt.sphere.models.UpdatePolicy": "Microsoft.AzureSphere.UpdatePolicy",
        "azure.mgmt.sphere.models.AllowCrashDumpCollection": "Microsoft.AzureSphere.AllowCrashDumpCollection",
        "azure.mgmt.sphere.models.CertificateStatus": "Microsoft.AzureSphere.CertificateStatus",
        "azure.mgmt.sphere.models.CapabilityType": "Microsoft.AzureSphere.CapabilityType",
        "azure.mgmt.sphere.AzureSphereMgmtClient.operations.list": "Azure.ResourceManager.Operations.list",
        "azure.mgmt.sphere.AzureSphereMgmtClient.catalogs.get": "Microsoft.AzureSphere.Catalogs.get",
        "azure.mgmt.sphere.AzureSphereMgmtClient.catalogs.begin_create_or_update": "Microsoft.AzureSphere.Catalogs.createOrUpdate",
        "azure.mgmt.sphere.AzureSphereMgmtClient.catalogs.update": "Microsoft.AzureSphere.Catalogs.update",
        "azure.mgmt.sphere.AzureSphereMgmtClient.catalogs.begin_delete": "Microsoft.AzureSphere.Catalogs.delete",
        "azure.mgmt.sphere.AzureSphereMgmtClient.catalogs.list_by_resource_group": "Microsoft.AzureSphere.Catalogs.listByResourceGroup",
        "azure.mgmt.sphere.AzureSphereMgmtClient.catalogs.list_by_subscription": "Microsoft.AzureSphere.Catalogs.listBySubscription",
        "azure.mgmt.sphere.AzureSphereMgmtClient.catalogs.count_devices": "Microsoft.AzureSphere.Catalogs.countDevices",
        "azure.mgmt.sphere.AzureSphereMgmtClient.catalogs.list_deployments": "Microsoft.AzureSphere.Catalogs.listDeployments",
        "azure.mgmt.sphere.AzureSphereMgmtClient.catalogs.list_device_groups": "Microsoft.AzureSphere.Catalogs.listDeviceGroups",
        "azure.mgmt.sphere.AzureSphereMgmtClient.catalogs.list_device_insights": "Microsoft.AzureSphere.Catalogs.listDeviceInsights",
        "azure.mgmt.sphere.AzureSphereMgmtClient.catalogs.list_devices": "Microsoft.AzureSphere.Catalogs.listDevices",
        "azure.mgmt.sphere.AzureSphereMgmtClient.catalogs.begin_upload_image": "Microsoft.AzureSphere.Catalogs.uploadImage",
        "azure.mgmt.sphere.AzureSphereMgmtClient.certificates.get": "Microsoft.AzureSphere.Certificates.get",
        "azure.mgmt.sphere.AzureSphereMgmtClient.certificates.list_by_catalog": "Microsoft.AzureSphere.Certificates.listByCatalog",
        "azure.mgmt.sphere.AzureSphereMgmtClient.certificates.retrieve_cert_chain": "Microsoft.AzureSphere.Certificates.retrieveCertChain",
        "azure.mgmt.sphere.AzureSphereMgmtClient.certificates.retrieve_proof_of_possession_nonce": "Microsoft.AzureSphere.Certificates.retrieveProofOfPossessionNonce",
        "azure.mgmt.sphere.AzureSphereMgmtClient.images.get": "Microsoft.AzureSphere.Images.get",
        "azure.mgmt.sphere.AzureSphereMgmtClient.images.begin_create_or_update": "Microsoft.AzureSphere.Images.createOrUpdate",
        "azure.mgmt.sphere.AzureSphereMgmtClient.images.begin_delete": "Microsoft.AzureSphere.Images.delete",
        "azure.mgmt.sphere.AzureSphereMgmtClient.images.list_by_catalog": "Microsoft.AzureSphere.Images.listByCatalog",
        "azure.mgmt.sphere.AzureSphereMgmtClient.products.get": "Microsoft.AzureSphere.Products.get",
        "azure.mgmt.sphere.AzureSphereMgmtClient.products.begin_create_or_update": "Microsoft.AzureSphere.Products.createOrUpdate",
        "azure.mgmt.sphere.AzureSphereMgmtClient.products.begin_update": "Microsoft.AzureSphere.Products.update",
        "azure.mgmt.sphere.AzureSphereMgmtClient.products.begin_delete": "Microsoft.AzureSphere.Products.delete",
        "azure.mgmt.sphere.AzureSphereMgmtClient.products.list_by_catalog": "Microsoft.AzureSphere.Products.listByCatalog",
        "azure.mgmt.sphere.AzureSphereMgmtClient.products.count_devices": "Microsoft.AzureSphere.Products.countDevices",
        "azure.mgmt.sphere.AzureSphereMgmtClient.products.generate_default_device_groups": "Microsoft.AzureSphere.Products.generateDefaultDeviceGroups",
        "azure.mgmt.sphere.AzureSphereMgmtClient.device_groups.get": "Microsoft.AzureSphere.DeviceGroups.get",
        "azure.mgmt.sphere.AzureSphereMgmtClient.device_groups.begin_create_or_update": "Microsoft.AzureSphere.DeviceGroups.createOrUpdate",
        "azure.mgmt.sphere.AzureSphereMgmtClient.device_groups.begin_update": "Microsoft.AzureSphere.DeviceGroups.update",
        "azure.mgmt.sphere.AzureSphereMgmtClient.device_groups.begin_delete": "Microsoft.AzureSphere.DeviceGroups.delete",
        "azure.mgmt.sphere.AzureSphereMgmtClient.device_groups.list_by_product": "Microsoft.AzureSphere.DeviceGroups.listByProduct",
        "azure.mgmt.sphere.AzureSphereMgmtClient.device_groups.begin_claim_devices": "Microsoft.AzureSphere.DeviceGroups.claimDevices",
        "azure.mgmt.sphere.AzureSphereMgmtClient.device_groups.count_devices": "Microsoft.AzureSphere.DeviceGroups.countDevices",
        "azure.mgmt.sphere.AzureSphereMgmtClient.deployments.get": "Microsoft.AzureSphere.Deployments.get",
        "azure.mgmt.sphere.AzureSphereMgmtClient.deployments.begin_create_or_update": "Microsoft.AzureSphere.Deployments.createOrUpdate",
        "azure.mgmt.sphere.AzureSphereMgmtClient.deployments.begin_delete": "Microsoft.AzureSphere.Deployments.delete",
        "azure.mgmt.sphere.AzureSphereMgmtClient.deployments.list_by_device_group": "Microsoft.AzureSphere.Deployments.listByDeviceGroup",
        "azure.mgmt.sphere.AzureSphereMgmtClient.devices.get": "Microsoft.AzureSphere.Devices.get",
        "azure.mgmt.sphere.AzureSphereMgmtClient.devices.begin_create_or_update": "Microsoft.AzureSphere.Devices.createOrUpdate",
        "azure.mgmt.sphere.AzureSphereMgmtClient.devices.begin_update": "Microsoft.AzureSphere.Devices.update",
        "azure.mgmt.sphere.AzureSphereMgmtClient.devices.begin_delete": "Microsoft.AzureSphere.Devices.delete",
        "azure.mgmt.sphere.AzureSphereMgmtClient.devices.list_by_device_group": "Microsoft.AzureSphere.Devices.listByDeviceGroup",
        "azure.mgmt.sphere.AzureSphereMgmtClient.devices.begin_generate_capability_image": "Microsoft.AzureSphere.Devices.generateCapabilityImage"
    }
}